my_method/__init__.py
my_method/common.py
my_method/directory_create/__init__.py
my_method/directory_create/directory_create.py
my_method/directory_listing/__init__.py
my_method/directory_listing/directory_listing.py
my_method/my_input/__init__.py
my_method/my_input/my_input.py
my_method/version_check/__init__.py
my_method/version_check/version_check.py
my_method/wav_ndarray/__init__.py
my_method/wav_ndarray/wav_ndarray.py
deize_method-2.3.4.dist-info/LICENSE
deize_method-2.3.4.dist-info/METADATA
deize_method-2.3.4.dist-info/WHEEL
deize_method-2.3.4.dist-info/RECORD
