Metadata-Version: 2.1
Name: deize-method
Version: 2.3.4
Summary: deizeが使用するメソッド
License: MIT
Author: Deize
Author-email: ddeize.git@gmail.com
Requires-Python: >=3.11,<4.0
Classifier: License :: OSI Approved :: MIT License
Classifier: Programming Language :: Python :: 3
Classifier: Programming Language :: Python :: 3.11
Classifier: Programming Language :: Python :: 3.12
Requires-Dist: numpy (>=1.26.4,<2.0.0)
